keepsake/__init__.py
keepsake/checkpoint.py
keepsake/console.py
keepsake/constants.py
keepsake/daemon.py
keepsake/exceptions.py
keepsake/experiment.py
keepsake/hash.py
keepsake/json.py
keepsake/keras_callback.py
keepsake/metadata.py
keepsake/packages.py
keepsake/pb_convert.py
keepsake/pl_callback.py
keepsake/project.py
keepsake/system.py
keepsake/validate.py
keepsake/version.py
keepsake/_vendor/__init__.py
keepsake/_vendor/dataclasses.py
keepsake/_vendor/typing_extensions.py
keepsake/_vendor/colors/__init__.py
keepsake/_vendor/colors/colors.py
keepsake/_vendor/colors/csscolors.py
keepsake/_vendor/colors/version.py
keepsake/_vendor/yaml/__init__.py
keepsake/_vendor/yaml/composer.py
keepsake/_vendor/yaml/constructor.py
keepsake/_vendor/yaml/cyaml.py
keepsake/_vendor/yaml/dumper.py
keepsake/_vendor/yaml/emitter.py
keepsake/_vendor/yaml/error.py
keepsake/_vendor/yaml/events.py
keepsake/_vendor/yaml/loader.py
keepsake/_vendor/yaml/nodes.py
keepsake/_vendor/yaml/parser.py
keepsake/_vendor/yaml/reader.py
keepsake/_vendor/yaml/representer.py
keepsake/_vendor/yaml/resolver.py
keepsake/_vendor/yaml/scanner.py
keepsake/_vendor/yaml/serializer.py
keepsake/_vendor/yaml/tokens.py
keepsake/bin/keepsake-shared
keepsake/servicepb/__init__.py
keepsake/servicepb/keepsake_pb2.py
keepsake/servicepb/keepsake_pb2_grpc.py
keepsake-0.4.2.data/scripts/keepsake
tests/__init__.py
tests/conftest.py
tests/factories.py
tests/test_checkpoint.py
tests/test_experiment.py
tests/test_hash.py
tests/test_keras_callback.py
tests/test_metadata.py
tests/test_packages.py
tests/test_pb_convert.py
tests/test_pl_callback.py
tests/test_plot.py
tests/test_python_package.py
keepsake-0.4.2.dist-info/METADATA
keepsake-0.4.2.dist-info/WHEEL
keepsake-0.4.2.dist-info/top_level.txt
keepsake-0.4.2.dist-info/RECORD
