Metadata-Version: 2.1
Name: keepsake
Version: 0.4.2
Summary: Version control for machine learning
Home-page: https://keepsake.ai
Author-email: team@replicate.ai
License: Apache License 2.0
Platform: UNKNOWN
Requires-Python: >=3.6.0
Requires-Dist: googleapis-common-protos[grpc] (>=1.0.0)
